{
  "revision" : 3,
  "compression" : false,
  "dataAnalyzer" : true,
  "replicas" : 1,
  "openApiUuid" : null,
  "currentProfileUuid" : "827bdf5a-a018-4e6b-b454-65b975d49930",
  "parameterGroupUuids" : [ ],
  "repoResourceUuids" : [ ],
  "routeDefinitions" : [ {
    "id" : 1,
    "camelRouteId" : "simple-integration",
    "enabled" : true,
    "routeId" : 1,
    "route" : [ {
      "name" : "timer",
      "nodeId" : "ecdb2fdf-298c-4f99-b5ee-27f5baac7f7a",
      "description" : "once per second",
      "properties" : {
        "_type" : "timer",
        "active" : true,
        "advancedParameters" : [ ],
        "camelGroup" : "component",
        "daemon" : true,
        "delay" : "1000",
        "fixedRate" : false,
        "name" : "timer",
        "period" : "1000",
        "repeatCount" : "0",
        "setScheduleTime" : false,
        "time" : "2021-12-31 00:00:00",
        "timerName" : "timer",
        "url" : ""
      },
      "_type" : "timer",
      "kameletPropertiesUrl" : "?timerName=timer&period=1000&repeatCount=0&delay=1000&fixedRate=false&daemon=true&setScheduleTime=false&time=2021-12-31 00:00:00"
    }, {
      "name" : "setBody",
      "nodeId" : "5aefdc84-3063-4fe4-a1df-7df2415e1f6a",
      "description" : "add exchangeId to body",
      "properties" : {
        "_type" : "setBody",
        "active" : true,
        "addNamespaces" : false,
        "camelGroup" : "core",
        "expression" : "test body from simple: ${exchangeId}",
        "language" : "Simple",
        "name" : "setBody",
        "namespaces" : [ ],
        "suppressExceptions" : false,
        "url" : ""
      },
      "_type" : "setBody",
      "kameletPropertiesUrl" : "?language=Simple&expression=test body from simple: ${exchangeId}&addNamespaces=false&suppressExceptions=false"
    }, {
      "name" : "messagingEndpoint",
      "nodeId" : "98bfeed3-7bf4-4abe-819c-63caf3f88306",
      "description" : "to route-2",
      "properties" : {
        "_type" : "messagingEndpoint",
        "active" : true,
        "camelGroup" : "core",
        "name" : "messagingEndpoint",
        "toDynamicEndpoint" : false,
        "uri" : "direct://route-2",
        "url" : ""
      },
      "_type" : "messagingEndpoint",
      "kameletPropertiesUrl" : "?uri=direct://route-2"
    } ]
  }, {
    "id" : 2,
    "camelRouteId" : "route-2",
    "enabled" : true,
    "routeId" : 2,
    "route" : [ {
      "name" : "direct",
      "nodeId" : "edc4610a-62a1-42f9-ba13-d640747c6f7d",
      "description" : "from route-2",
      "properties" : {
        "_type" : "direct",
        "active" : true,
        "advancedParameters" : [ ],
        "camelGroup" : "core",
        "endpointName" : "route-2",
        "name" : "direct",
        "url" : ""
      },
      "_type" : "direct",
      "kameletPropertiesUrl" : "?endpointName=route-2"
    }, {
      "name" : "setHeaders",
      "nodeId" : "6f7afc93-e380-4389-862a-53a0722d19a7",
      "description" : "set id=${camelId}",
      "properties" : {
        "_type" : "setHeaders",
        "active" : true,
        "addNamespaces" : false,
        "camelGroup" : "core",
        "headerList" : [ {
          "headerName" : "id",
          "headerValue" : "${camelId}",
          "language" : "Simple"
        } ],
        "name" : "setHeaders",
        "namespaces" : [ ],
        "suppressExceptions" : false,
        "url" : ""
      },
      "_type" : "setHeaders",
      "kameletPropertiesUrl" : "?addNamespaces=false&suppressExceptions=false"
    }, {
      "name" : "dslProcessor",
      "nodeId" : "b7f307ca-4d45-401a-9fcd-14de4ce4f2ad",
      "description" : "to route-3",
      "properties" : {
        "_type" : "dslProcessor",
        "active" : true,
        "camelGroup" : "core",
        "dsl" : ".to('direct://route-3')",
        "name" : "dslProcessor",
        "url" : ""
      },
      "_type" : "dslProcessor",
      "kameletPropertiesUrl" : "?dsl=.to('direct://route-3')"
    } ]
  }, {
    "id" : 3,
    "camelRouteId" : "route-3",
    "enabled" : true,
    "routeId" : 3,
    "route" : [ {
      "name" : "dslProcessor",
      "nodeId" : "a8d0d24d-281f-41e9-b406-3f6c47ab458e",
      "description" : "from route-3",
      "properties" : {
        "_type" : "dslProcessor",
        "active" : true,
        "camelGroup" : "core",
        "dsl" : "from('direct://route-3')",
        "name" : "dslProcessor",
        "url" : ""
      },
      "_type" : "dslProcessor",
      "kameletPropertiesUrl" : "?dsl=from('direct://route-3')"
    }, {
      "name" : "process",
      "nodeId" : "7a5cc60c-04a2-4540-8f2d-81e7e96251ae",
      "description" : "add date to headers",
      "properties" : {
        "_type" : "process",
        "active" : true,
        "camelGroup" : "transform",
        "code" : "exchange.getIn().setHeader(\"date\", new Date())",
        "import" : "",
        "name" : "process",
        "url" : ""
      },
      "_type" : "process",
      "kameletPropertiesUrl" : "?code=exchange.getIn().setHeader(\"date\", new Date())"
    }, {
      "name" : "log",
      "nodeId" : "f392dc09-8d3e-47eb-a14a-9eb8e576ddee",
      "description" : "EIP log",
      "properties" : {
        "_type" : "log",
        "active" : true,
        "advancedParameters" : [ ],
        "camelGroup" : "component",
        "level" : "INFO",
        "logType" : "EIP",
        "loggerName" : "log",
        "message" : "headers1: ${headers}; body1: ${body}",
        "multiline" : false,
        "name" : "log",
        "showAll" : false,
        "showBody" : true,
        "showBodyType" : true,
        "showCaughtException" : false,
        "showExchangeId" : false,
        "showHeaders" : false,
        "showProperties" : false,
        "showStackTrace" : false,
        "toDynamicEndpoint" : false,
        "url" : ""
      },
      "_type" : "log",
      "kameletPropertiesUrl" : "?loggerName=log&level=INFO&logType=EIP&multiline=false&showAll=false&showBody=true&showBodyType=true&showCaughtException=false&showExchangeId=false&showHeaders=false&showProperties=false&showStackTrace=false&message=headers1: ${headers}; body1: ${body}"
    } ]
  } ],
  "traits" : [ ],
  "id" : "8d62b7db-e749-4330-8f7c-b2c06cf9d754",
  "name" : "simple-integration-46346404",
  "description" : "Simple integration with the timer-body-log example",
  "createdAt" : "2023-09-08T12:41:49.668429375",
  "updatedAt" : "2023-09-24T19:05:33.9362932",
  "createdBy" : "123e4567-e89b-12d3-a456-426655440010",
  "updatedBy" : "123e4567-e89b-12d3-a456-426655440010"
}